fish_scan/__init__.py
fish_scan/_reader.py
fish_scan/_sample_data.py
fish_scan/_widget.py
fish_scan/_writer.py
fish_scan/functions.py
fish_scan/napari.yaml
fish_scan/_tests/__init__.py
fish_scan/_tests/test_reader.py
fish_scan/_tests/test_sample_data.py
fish_scan/_tests/test_widget.py
fish_scan/_tests/test_writer.py
fish_scan/support_files/.DS_Store
fish_scan/support_files/landmarks.png
fish_scan/support_files/landmarks_boxes.png
fish_scan-1.1.0.dist-info/LICENSE
fish_scan-1.1.0.dist-info/METADATA
fish_scan-1.1.0.dist-info/WHEEL
fish_scan-1.1.0.dist-info/entry_points.txt
fish_scan-1.1.0.dist-info/top_level.txt
fish_scan-1.1.0.dist-info/RECORD
