Metadata-Version: 2.1
Name: fish-scan
Version: 1.1.0
Summary: Plugin to enhance fish detection and analysis for underwater research
Home-page: https://github.com/ariannaravera/fish-scan
Author: Arianna Ravera
Author-email: ariannaravera22@gmail.com
License: 
Project-URL: Bug Tracker, https://github.com/ariannaravera/fish-scan/issues
Project-URL: Documentation, https://github.com/ariannaravera/fish-scan#README.md
Project-URL: Source Code, https://github.com/ariannaravera/fish-scan
Project-URL: User Support, https://github.com/ariannaravera/fish-scan/issues
Classifier: Development Status :: 2 - Pre-Alpha
Classifier: Framework :: napari
Classifier: Intended Audience :: Developers
Classifier: License :: OSI Approved :: BSD License
Classifier: Operating System :: OS Independent
Classifier: Programming Language :: Python
Classifier: Programming Language :: Python :: 3
Classifier: Programming Language :: Python :: 3 :: Only
Classifier: Programming Language :: Python :: 3.9
Classifier: Programming Language :: Python :: 3.10
Classifier: Programming Language :: Python :: 3.11
Classifier: Programming Language :: Python :: 3.12
Classifier: Topic :: Scientific/Engineering :: Image Processing
Requires-Python: >=3.9
License-File: LICENSE
Requires-Dist: numpy
Requires-Dist: magicgui
Requires-Dist: qtpy
Requires-Dist: scikit-image
Requires-Dist: opencv-python
Requires-Dist: matplotlib
Requires-Dist: scikit-learn
Provides-Extra: testing
Requires-Dist: tox ; extra == 'testing'
Requires-Dist: pytest ; extra == 'testing'
Requires-Dist: pytest-cov ; extra == 'testing'
Requires-Dist: pytest-qt ; extra == 'testing'
Requires-Dist: napari ; extra == 'testing'
Requires-Dist: pyqt5 ; extra == 'testing'
